enhance_this/__init__.py
enhance_this/cli.py
enhance_this/clipboard.py
enhance_this/config.py
enhance_this/enhancer.py
enhance_this/history.py
enhance_this/ollama_client.py
enhance_this/templates/__init__.py
enhance_this/templates/bullets.txt
enhance_this/templates/casual.txt
enhance_this/templates/concise.txt
enhance_this/templates/creative.txt
enhance_this/templates/detailed.txt
enhance_this/templates/formal.txt
enhance_this/templates/json.txt
enhance_this/templates/summary.txt
enhance_this/templates/technical.txt
enhance_this-0.3.0.dist-info/licenses/LICENSE
enhance_this-0.3.0.dist-info/METADATA
enhance_this-0.3.0.dist-info/WHEEL
enhance_this-0.3.0.dist-info/entry_points.txt
enhance_this-0.3.0.dist-info/top_level.txt
enhance_this-0.3.0.dist-info/RECORD
