Metadata-Version: 2.4
Name: enhance-this
Version: 0.3.0
Summary: A CLI tool to enhance prompts using Ollama AI.
Author-email: Hariharen <thisishariharen@gmail.com>
Project-URL: Homepage, https://github.com/hariharen9/enhance-this
Project-URL: Bug Tracker, https://github.com/hariharen9/enhance-this/issues
Classifier: Programming Language :: Python :: 3
Classifier: License :: OSI Approved :: MIT License
Classifier: Operating System :: OS Independent
Requires-Python: >=3.8
License-File: LICENSE
Requires-Dist: click>=8.0.0
Requires-Dist: requests>=2.25.0
Requires-Dist: pyyaml>=6.0
Requires-Dist: pyperclip>=1.8.0
Requires-Dist: rich>=10.0.0
Requires-Dist: questionary>=1.10.0
Requires-Dist: importlib-resources; python_version < "3.9"
Dynamic: license-file
